codec_Watteco/Decoding_Functions.py
codec_Watteco/Main.py
codec_Watteco/Scroll_Decoding_Functions.py
codec_Watteco/WTC_CodecTools.py
codec_Watteco/ZCL.py
codec_Watteco/ZCL_FRAME.py
codec_Watteco/_TestsTools.py
codec_Watteco/_ValidationTests.py
codec_Watteco/__init__.py
codec_Watteco/essai_TICs_TMP.py
codec_Watteco/test.py
codec_Watteco/TICs/TIC_CBE.py
codec_Watteco/TICs/TIC_ICE.py
codec_Watteco/TICs/TIC_PMEPMI.py
codec_Watteco/TICs/TIC_STD.py
codec_Watteco/TICs/_TIC_Tools.py
codec_Watteco/TICs/_TIC_Types.py
codec_Watteco/TICs/__init__.py
codec_Watteco-0.0.9.dist-info/LICENSE
codec_Watteco-0.0.9.dist-info/METADATA
codec_Watteco-0.0.9.dist-info/WHEEL
codec_Watteco-0.0.9.dist-info/top_level.txt
codec_Watteco-0.0.9.dist-info/RECORD
